pysnoonotes/__init__.py
pysnoonotes/auth.py
pysnoonotes/core.py
pysnoonotes/errors.py
tests/__init__.py
tests/test_main.py
pysnoonotes-1.1.0.dist-info/LICENSE
pysnoonotes-1.1.0.dist-info/METADATA
pysnoonotes-1.1.0.dist-info/WHEEL
pysnoonotes-1.1.0.dist-info/top_level.txt
pysnoonotes-1.1.0.dist-info/RECORD
