Metadata-Version: 2.1
Name: pysnoonotes
Version: 1.1.0
Summary: A Python wrapper for the Snoonotes API
Home-page: https://github.com/mmshivesh/pysnoonotes
Author: mmshivesh
Author-email: 
License: UNKNOWN
Platform: UNKNOWN
Classifier: Programming Language :: Python :: 3
Classifier: License :: OSI Approved :: MIT License
Classifier: Operating System :: OS Independent
Requires-Python: >=3.6
Requires-Dist: requests (==2.23.0)
